LICENSE
README.md
setup.py
podb/DB.py
podb/__init__.py
podb.egg-info/PKG-INFO
podb.egg-info/SOURCES.txt
podb.egg-info/dependency_links.txt
podb.egg-info/requires.txt
podb.egg-info/top_level.txt
tests/DBEntryTests.py
tests/DBTests.py
tests/__init__.py
tests/all.py
tests/huge.py
tests/mongocomp.py
tests/processed.py
tests/threaded.py