Metadata-Version: 2.1
Name: podb
Version: 1.51
Summary: python object database
Home-page: https://github.com/nbdy/podb
Author: Pascal Eberlein
Author-email: pascal@eberlein.io
License: UNKNOWN
Keywords: python object database
Platform: UNKNOWN
Classifier: Development Status :: 3 - Alpha
Classifier: Intended Audience :: Developers
Classifier: Topic :: Software Development :: Build Tools
Classifier: License :: OSI Approved :: MIT License
Classifier: Programming Language :: Python :: 3.6
License-File: LICENSE
